<?xml version="1.0" encoding="UTF-8"?>
<objects serializationModel="Studio.02.03.00">
	<object class="AudioFile" id="{9b744083-323c-4c9b-b805-d93b41d56a36}">
		<property name="assetPath">
			<value>Environmental Sounds/Lock Sound.mp3</value>
		</property>
		<property name="frequencyInKHz">
			<value>24</value>
		</property>
		<property name="channelCount">
			<value>2</value>
		</property>
		<property name="length">
			<value>0.69599999999999995</value>
		</property>
		<relationship name="masterAssetFolder">
			<destination>{b9931ff9-f8a1-4afb-bf53-e3007af6bc87}</destination>
		</relationship>
	</object>
</objects>
